setup.py
ia32_python/__init__.py
ia32_python.egg-info/PKG-INFO
ia32_python.egg-info/SOURCES.txt
ia32_python.egg-info/dependency_links.txt
ia32_python.egg-info/requires.txt
ia32_python.egg-info/top_level.txt
ia32_python/intel_manual/__init__.py
ia32_python/intel_manual/apic/__init__.py
ia32_python/intel_manual/control_registers/__init__.py
ia32_python/intel_manual/cpuid/__init__.py
ia32_python/intel_manual/cpuid/cpuid_eax_0d/__init__.py
ia32_python/intel_manual/cpuid/cpuid_eax_0f/__init__.py
ia32_python/intel_manual/cpuid/cpuid_eax_10/__init__.py
ia32_python/intel_manual/cpuid/cpuid_eax_12/__init__.py
ia32_python/intel_manual/cpuid/cpuid_eax_14/__init__.py
ia32_python/intel_manual/cpuid/cpuid_eax_17/__init__.py
ia32_python/intel_manual/cpuid/cpuid_eax_18/__init__.py
ia32_python/intel_manual/debug_registers/__init__.py
ia32_python/intel_manual/exceptions/__init__.py
ia32_python/intel_manual/memory_type/__init__.py
ia32_python/intel_manual/model_specific_registers/__init__.py
ia32_python/intel_manual/model_specific_registers/ia32_a_pmc/__init__.py
ia32_python/intel_manual/model_specific_registers/ia32_fixed_ctr/__init__.py
ia32_python/intel_manual/model_specific_registers/ia32_mc_addr/__init__.py
ia32_python/intel_manual/model_specific_registers/ia32_mc_ctl/__init__.py
ia32_python/intel_manual/model_specific_registers/ia32_mc_ctl2/__init__.py
ia32_python/intel_manual/model_specific_registers/ia32_mc_misc/__init__.py
ia32_python/intel_manual/model_specific_registers/ia32_mc_status/__init__.py
ia32_python/intel_manual/model_specific_registers/ia32_mtrr_fix/__init__.py
ia32_python/intel_manual/model_specific_registers/ia32_mtrr_fix/ia32_mtrr_fix16k/__init__.py
ia32_python/intel_manual/model_specific_registers/ia32_mtrr_fix/ia32_mtrr_fix4k/__init__.py
ia32_python/intel_manual/model_specific_registers/ia32_mtrr_fix/ia32_mtrr_fix64k/__init__.py
ia32_python/intel_manual/model_specific_registers/ia32_mtrr_physbase/__init__.py
ia32_python/intel_manual/model_specific_registers/ia32_mtrr_physmask/__init__.py
ia32_python/intel_manual/model_specific_registers/ia32_p5_mc/__init__.py
