Metadata-Version: 1.0
Name: ia32-python
Version: 1.0.5
Summary: x86-64 definitions for Python 2/3
Home-page: https://github.com/guye1296/ia32-python
Author: guye1296
Author-email: UNKNOWN
License: UNKNOWN
Platform: UNKNOWN
